docs/api.rst
docs/authors.rst
docs/conf.py
docs/contributing.rst
docs/file_structure.md
docs/history.rst
docs/index.rst
docs/installation.rst
docs/make.bat
docs/modules.rst
docs/recipe.md
docs/setup.md
docs/sources.md
docs/usage.rst
docs/user_config.md
docs/_build/doctrees/api.doctree
docs/_build/doctrees/authors.doctree
docs/_build/doctrees/contributing.doctree
docs/_build/doctrees/environment.pickle
docs/_build/doctrees/file_structure.doctree
docs/_build/doctrees/history.doctree
docs/_build/doctrees/index.doctree
docs/_build/doctrees/installation.doctree
docs/_build/doctrees/modules.doctree
docs/_build/doctrees/recipe.doctree
docs/_build/doctrees/setup.doctree
docs/_build/doctrees/sources.doctree
docs/_build/doctrees/usage.doctree
docs/_build/doctrees/user_config.doctree
docs/_build/doctrees/generated/modules.doctree
docs/_build/doctrees/generated/shoestring_assembler.doctree
docs/_build/doctrees/generated/shoestring_assembler.engine.doctree
docs/_build/doctrees/generated/shoestring_assembler.interface.doctree
docs/_build/doctrees/generated/shoestring_assembler.interface.events.doctree
docs/_build/doctrees/generated/shoestring_assembler.model.doctree
docs/_build/doctrees/generated/shoestring_assembler.model.schemas.doctree
docs/_build/doctrees/generated/shoestring_assembler.view.cli_app.components.doctree
docs/_build/doctrees/generated/shoestring_assembler.view.cli_app.doctree
docs/_build/doctrees/generated/shoestring_assembler.view.cli_app.screens.doctree
docs/_build/doctrees/generated/shoestring_assembler.view.doctree
docs/_build/doctrees/generated/shoestring_assembler.view.plain_cli.doctree
docs/_build/markdown/api.md
docs/_build/markdown/authors.md
docs/_build/markdown/contributing.md
docs/_build/markdown/file_structure.md
docs/_build/markdown/history.md
docs/_build/markdown/index.md
docs/_build/markdown/installation.md
docs/_build/markdown/modules.md
docs/_build/markdown/recipe.md
docs/_build/markdown/setup.md
docs/_build/markdown/sources.md
shoestring_assembler-0.2.7.dist-info/licenses/AUTHORS.rst
shoestring_assembler-0.2.7.dist-info/licenses/LICENSE
shoestring_assembler-0.2.7.dist-info/METADATA
shoestring_assembler-0.2.7.dist-info/WHEEL
shoestring_assembler-0.2.7.dist-info/entry_points.txt
shoestring_assembler-0.2.7.dist-info/top_level.txt
shoestring_assembler-0.2.7.dist-info/RECORD
